odoo10_addon_account_payment_sale-10.0.1.1.0-py2.7-nspkg.pth
odoo/addons/account_payment_sale/README.rst
odoo/addons/account_payment_sale/__init__.py
odoo/addons/account_payment_sale/__manifest__.py
odoo/addons/account_payment_sale/i18n/ca.po
odoo/addons/account_payment_sale/i18n/da_DK.po
odoo/addons/account_payment_sale/i18n/de.po
odoo/addons/account_payment_sale/i18n/es.po
odoo/addons/account_payment_sale/i18n/fr.po
odoo/addons/account_payment_sale/i18n/nl.po
odoo/addons/account_payment_sale/i18n/nl_NL.po
odoo/addons/account_payment_sale/i18n/pt_BR.po
odoo/addons/account_payment_sale/i18n/sl.po
odoo/addons/account_payment_sale/models/__init__.py
odoo/addons/account_payment_sale/models/sale_order.py
odoo/addons/account_payment_sale/static/description/icon.png
odoo/addons/account_payment_sale/views/sale_order_view.xml
odoo/addons/account_payment_sale/views/sale_report_templates.xml
odoo/addons/account_payment_sale/wizard/__init__.py
odoo/addons/account_payment_sale/wizard/sale_make_invoice_advance.py
odoo10_addon_account_payment_sale-10.0.1.1.0.dist-info/DESCRIPTION.rst
odoo10_addon_account_payment_sale-10.0.1.1.0.dist-info/METADATA
odoo10_addon_account_payment_sale-10.0.1.1.0.dist-info/RECORD
odoo10_addon_account_payment_sale-10.0.1.1.0.dist-info/WHEEL
odoo10_addon_account_payment_sale-10.0.1.1.0.dist-info/metadata.json
odoo10_addon_account_payment_sale-10.0.1.1.0.dist-info/namespace_packages.txt
odoo10_addon_account_payment_sale-10.0.1.1.0.dist-info/top_level.txt
